{
    "commands": [
        {
            "name": "ruletarusa",
            "cmd": "ruletarusa",
            "func": "ruletarusa",
            "type": "reserved",
            "description": "Tiraras del gatillo y si tenia bala te mueres",
            "cooldown": 10,
            "canTimeout": false,
            "canTimeoutMods": false,
            "canGiveMod": false
        },
        {
            "name": "annoucement",
            "cmd": "anuncio",
            "func": "anuncio",
            "type": "reserved",
            "cooldown": 10,
            "userLevelName": "mod",
            "userLevel": 6,
            "description": "Anuncia algo en el canal"
        },
        {
            "name": "promo",
            "cmd": "promo",
            "func": "promo",
            "type": "reserved",
            "cooldown": 10,
            "userLevelName": "mod",
            "userLevel": 6,
            "description": "Es otra forma de lanzar un shoutout pero sin activar el shoutout y la respuesta es por texto en vez de por anuncio para que los que esten en movil puedan ver el mensaje",
            "showClip": true
        },
        {
            "name": "shoutout",
            "cmd": "so",
            "func": "shoutout",
            "type": "reserved",
            "cooldown": 10,
            "userLevelName": "mod",
            "userLevel": 6,
            "description": "Menciona a un usuario y si tienes activado lo de los clips mandara un clip al canal",
            "showClip": true
        },
        {
            "name": "Create Prediction",
            "cmd": "predi",
            "func": "predi",
            "type": "reserved",
            "cooldown": 10,
            "userLevelName": "mod",
            "userLevel": 6,
            "description": "Crea una prediccion con la siguiente sintaxis: !predi <titulo>;<opcion1>/<opcion2>;<tiempo en segundos> | Ejemplo: !predi 多Ganara el streamer?;Si/No;60 | El tiempo maximo es de 5 minutos y minimo de 30 segundos | El titulo no puede ser mayor a 100 caracteres | Las opciones no pueden ser mayor a 100 caracteres | Minimo 2 opciones y maximo 10 opciones y deben ser separadas por /"
        },
        {
            "name": "End Prediction",
            "cmd": "endpredi",
            "func": "endpredi",
            "type": "reserved",
            "cooldown": 10,
            "userLevelName": "mod",
            "userLevel": 6,
            "description": "Termina la prediccion actual y da el resultado ganador | Ejemplo: !endpredi <numero de opcion> | Ejemplo: !endpredi 1 | El numero de opcion debe ser el numero de la opcion ganadora"
        },
        {
            "name": "Cancel Prediction",
            "cmd": "cancelpredi",
            "func": "cancelpredi",
            "type": "reserved",
            "cooldown": 10,
            "userLevelName": "mod",
            "userLevel": 6,
            "description": "Cancela la prediccion actual | Ejemplo: !cancelpredi | No necesita argumentos | Solo funciona si la prediccion esta activa o si esta bloqueada"
        },
        {
            "name": "Lock Prediction",
            "cmd": "lockpredi",
            "func": "lockpredi",
            "type": "reserved",
            "cooldown": 10,
            "userLevelName": "mod",
            "userLevel": 6,
            "description": "Bloquea la prediccion actual lo cual inhabilita que los usuarios puedan votar | Ejemplo: !lockpredi | No necesita argumentos | Solo funciona si la prediccion esta activa"
        },
        {
            "name": "Create Poll",
            "cmd": "poll",
            "func": "poll",
            "type": "reserved",
            "cooldown": 10,
            "userLevelName": "mod",
            "userLevel": 6,
            "description": "Crea una encuesta con la siguiente sintaxis: !poll <titulo>;<opcion1>/<opcion2>;<tiempo en segundos> | Ejemplo: !poll 多Ganara el streamer?;Si/No;60 | El tiempo maximo es de 5 minutos y minimo de 30 segundos | El titulo no puede ser mayor a 100 caracteres | Las opciones no pueden ser mayor a 100 caracteres | Minimo 2 opciones y maximo 5 opciones y deben ser separadas por /"
        },
        {
            "name": "End Poll",
            "cmd": "endpoll",
            "func": "endpoll",
            "type": "reserved",
            "cooldown": 10,
            "userLevelName": "mod",
            "userLevel": 6,
            "description": "Termina la encuesta actual | Ejemplo: !endpoll | No necesita argumentos | Solo funciona si la encuesta esta activa"
        },
        {
            "name": "Cancel Poll",
            "cmd": "cancelpoll",
            "func": "cancelpoll",
            "type": "reserved",
            "cooldown": 10,
            "userLevelName": "mod",
            "userLevel": 6,
            "description": "Cancela la encuesta actual | Ejemplo: !cancelpoll | No necesita argumentos | Solo funciona si la encuesta esta activa"
        },
        {
            "name": "Change Game",
            "cmd": "game",
            "func": "game",
            "type": "reserved",
            "cooldown": 10,
            "userLevelName": "mod",
            "userLevel": 6,
            "description": "Cambia el juego actual | Ejemplo: !game <nombre del juego> | Ejemplo: !game Fortnite"
        },
        {
            "name": "Change Title",
            "cmd": "title",
            "func": "title",
            "type": "reserved",
            "cooldown": 10,
            "userLevelName": "mod",
            "userLevel": 6,
            "description": "Cambia el titulo actual | Ejemplo: !title <titulo> | Ejemplo: !title Hola como estas"
        },
        {
            "name": "Speach Chat",
            "cmd": "s",
            "func": "speach",
            "type": "reserved",
            "cooldown": 0,
            "enabled": false,
            "description": "Habla en el chat | Ejemplo: !s <mensaje> | Ejemplo: !s Hola como estas"
        },
        {
            "name": "Sumimetro",
            "cmd": "sumimetro",
            "func": "sumimetro",
            "type": "reserved",
            "cooldown": 10,
            "description": "Te da tu lectura de sumimetro que va desde 0% hasta 100% en cuanto a dominante o sumiso | Ejemplo: !sumimetro | Ejemplo de respuesta: (user) ha salido 65% sumiso y 35% dominante | Si se pasa un nombre de usuario como argumento te da la lectura de sumimetro de ese usuario | Ejemplo: !sumimetro (user) | Ejemplo de respuesta: (user) ha salido 65% sumiso y 35% dominante"
        },
        {
            "name": "Memide",
            "cmd": "memide",
            "func": "memide",
            "type": "reserved",
            "cooldown": 10,
            "description": "Te da tu supuesta medida de tu imaginario miembro viril | Ejemplo: !memide | Ejemplo de respuesta: (user) le mide 15cm | No necesita argumentos"
        },
        {
            "name": "amor",
            "cmd": "amor",
            "func": "amor",
            "type": "reserved",
            "cooldown": 10,
            "description": "Te dice cuanto amor hay entre dos usuarios | Ejemplo: !amor (touser) | Ejemplo: !amor <nombre de usuario> | Ejemplo de respuesta: (user) y (touser) tienen 100% de amor | Si se pasan dos nombres de usuario como argumentos te dice cuanto amor hay entre esos dos usuarios | Ejemplo: !amor (user) (touser) | Ejemplo de respuesta: (user) y (touser) tienen 100% de amor | Si se pasa el mismo nombre de usuario que utilizo el comando como argumento le dira una frase negativa | Ejemplo: !amor (user) | Ejemplo de respuesta: (user) no se puede amar a si mismo | Si no se pasa ningun argumento se le dara un recordatorio de como se usa el comando y le dira algo negativo | Ejemplo: !amor | Ejemplo de respuesta: (user) debes pasar un nombre de usuario como argumento, por eso te quedaras solo"
        },
        {
            "name": "ponerla",
            "cmd": "ponerla",
            "func": "ponerla",
            "type": "reserved",
            "cooldown": 10,
            "description": "Te dice el porcentaje de posibilidades de que pongas la | Ejemplo: !ponerla | Ejemplo de respuesta: (user) tiene 100% de posibilidades de ponerla | No necesita argumentos"
        },
        {
            "name": "Me cabe",
            "cmd": "mecabe",
            "func": "mecabe",
            "type": "reserved",
            "cooldown": 10,
            "description": "Te dice que tan grande de un miembro viril te cabe mas un texto extra | Ejemplo: !mecabe | Ejemplo de respuesta: (user) te cabe 15cm | No necesita argumentos"
        },
        {
            "name": "Only Emotes",
            "cmd": "onlyemotes",
            "func": "onlyemotes",
            "type": "reserved",
            "cooldown": 10,
            "userLevelName": "mod",
            "userLevel": 6,
            "description": "Activa o desactiva el modo solo emotes | Ejemplo: !onlyemotes | Ejemplo de respuesta: El modo solo emotes esta activado | No necesita argumentos"
        },
        {
            "name": "Create Custom Command",
            "cmd": "cc",
            "func": "createCommand",
            "type": "reserved",
            "cooldown": 10,
            "userLevelName": "mod",
            "userLevel": 6,
            "description": "Crea un comando personalizado con la siguiente sintaxis: !cc <nombre del comando> <funcion del comando> | Ejemplo: !cc <nombre del comando> <respuesta que dara el comando> | Ejemplo: !cc discord Sigueme en mi discord: discord.cdom201.com | Ejemplo de uso: !discord | Ejemplo de respuesta: Sigueme en mi discord: discord.cdom201.com | El nombre del comando no puede tener espacios ni contener caracteres especiales y no puede ser mayor a 20 caracteres | La funcion del comando no puede ser mayor a 300 caracteres | se le puede pasar opciones de configuracion antes del nombre del comando | Ejemplo: !cc -cd=10 -ul=mod <nombre del comando> <funcion del comando> | Ejemplo: !cc -cd=10 -ul=mod discord Sigueme en mi discord: discord.cdom201.com | Las opciones de configuracion son: -cd=cooldown, -ul=userlevel, -enabled=enabled, -desc=description | Las opciones de configuracion son opcionales | Si no se pasa ninguna opcion de configuracion se usaran las opciones por defecto | Si se pasa una opcion de configuracion se usara esa opcion de configuracion | Si se pasan varias opciones de configuracion se usaran todas las opciones de configuracion que se pasaron"
        },
        {
            "name": "Delete Custom Command",
            "cmd": "dc",
            "func": "deleteCommand",
            "type": "reserved",
            "cooldown": 10,
            "userLevelName": "mod",
            "userLevel": 6,
            "description": "Elimina un comando personalizado | Ejemplo: !dc <nombre del comando> | Ejemplo: !dc discord | Ejemplo de respuesta: El comando !discord ha sido eliminado"
        },
        {
            "name": "Edit Custom Command",
            "cmd": "ec",
            "func": "editCommand",
            "type": "reserved",
            "cooldown": 10,
            "userLevelName": "mod",
            "userLevel": 6,
            "description": "Edita un comando personalizado con la siguiente sintaxis: !ec <nombre del comando> <funcion del comando> | Ejemplo: !ec <nombre del comando> <respuesta que dara el comando> | Ejemplo: !ec discord Sigueme en mi discord: discord.cdom201.com | Ejemplo de uso: !discord | Ejemplo de respuesta: Sigueme en mi discord: discord.cdom201.com | El nombre del comando no puede tener espacios ni contener caracteres especiales y no puede ser mayor a 20 caracteres | La funcion del comando no puede ser mayor a 300 caracteres | se le puede pasar opciones de configuracion antes del nombre del comando | Ejemplo: !ec -cd=10 -ul=mod <nombre del comando> <funcion del comando> | Ejemplo: !ec -cd=10 -ul=mod discord Sigueme en mi discord: discord.cdom201.com | Las opciones de configuracion son: -cd=cooldown, -ul=userlevel, -enabled=enabled, -desc=description | Las opciones de configuracion son opcionales | Si no se pasa ninguna opcion de configuracion se usaran las opciones por defecto | Si se pasa una opcion de configuracion se usara esa opcion de configuracion | Si se pasan varias opciones de configuracion se usaran todas las opciones de configuracion que se pasaron"
        },
        {
            "name": "Follow Age",
            "cmd": "followage",
            "func": "followAge",
            "type": "reserved",
            "cooldown": 10,
            "description": "Te dice cuanto tiempo llevas siguiendo al canal | Ejemplo: !followage | Ejemplo de respuesta: (user) lleva siguiendo al canal 1 a単o, 2 meses y 3 dias | Si se pasa un nombre de usuario como argumento te dice cuanto tiempo lleva siguiendo al canal ese usuario | Ejemplo: !followage (user) | Ejemplo de respuesta: (user) lleva siguiendo al canal 1 a単o, 2 meses y 3 dias"
        },
        {
            "name": "Create clip",
            "cmd": "clip",
            "func": "createClip",
            "type": "reserved",
            "cooldown": 10,
            "enabled": false,
            "description": "Crea un clip del streamer con una duracion de 30 segundos despues de usar el comando | Ejemplo: !clip | Ejemplo de respuesta: Guardando clip... | Si la funcion es exitosa la respuesta dira Clip guardado con exito | No necesita argumentos"
        }
    ]
}